checkmytex/__init__.py
checkmytex/__main__.py
checkmytex/analyze.py
checkmytex/analyzed_document.py
checkmytex/document_analyzer.py
checkmytex/german.py
checkmytex/py.typed
checkmytex/cli/__init__.py
checkmytex/cli/arguments.py
checkmytex/cli/cli.py
checkmytex/cli/rich_printer.py
checkmytex/filtering/__init__.py
checkmytex/filtering/authors.py
checkmytex/filtering/code_listings.py
checkmytex/filtering/filter.py
checkmytex/filtering/math_mode.py
checkmytex/filtering/whitelist.py
checkmytex/finding/__init__.py
checkmytex/finding/abstract_checker.py
checkmytex/finding/chktex.py
checkmytex/finding/cleveref.py
checkmytex/finding/languagetool.py
checkmytex/finding/line_length.py
checkmytex/finding/nphard.py
checkmytex/finding/problem.py
checkmytex/finding/proselint.py
checkmytex/finding/siunitx.py
checkmytex/finding/spellcheck.py
checkmytex/finding/todo_checker.py
checkmytex/latex_document/__init__.py
checkmytex/latex_document/detex.py
checkmytex/latex_document/indexed_string.py
checkmytex/latex_document/latex_document.py
checkmytex/latex_document/origin.py
checkmytex/latex_document/parser.py
checkmytex/latex_document/source.py
checkmytex/reporting/__init__.py
checkmytex/reporting/extension_base.py
checkmytex/reporting/html_report.py
checkmytex/reporting/extensions/__init__.py
checkmytex/reporting/extensions/basic_message.py
checkmytex/reporting/extensions/chatgpt_link.py
checkmytex/reporting/extensions/lookup_url.py
checkmytex/utils/__init__.py
checkmytex/utils/choice.py
checkmytex/utils/editor.py
checkmytex-1.0.0.dist-info/licenses/LICENSE
checkmytex-1.0.0.dist-info/METADATA
checkmytex-1.0.0.dist-info/WHEEL
checkmytex-1.0.0.dist-info/entry_points.txt
checkmytex-1.0.0.dist-info/top_level.txt
checkmytex-1.0.0.dist-info/RECORD
