Metadata-Version: 2.4
Name: CheckMyTex
Version: 1.0.0
Summary: A simple tool for checking complex LaTeX documents, e.g., dissertations.
Author-email: Dominik Krupke <krupke@ibr.cs.tu-bs.de>
License: MIT
Project-URL: Homepage, https://github.com/d-krupke/checkmytex
Project-URL: Repository, https://github.com/d-krupke/checkmytex
Project-URL: Issues, https://github.com/d-krupke/checkmytex/issues
Keywords: LaTeX,spell-check,grammar-check,document-quality
Classifier: Development Status :: 5 - Production/Stable
Classifier: License :: OSI Approved :: MIT License
Classifier: Programming Language :: Python :: 3
Classifier: Programming Language :: Python :: 3.10
Classifier: Programming Language :: Python :: 3.11
Classifier: Programming Language :: Python :: 3.12
Classifier: Programming Language :: Python :: 3.13
Requires-Python: >=3.10
License-File: LICENSE
Requires-Dist: pyspellchecker>=0.7.2
Requires-Dist: flachtex>=0.3.13
Requires-Dist: yalafi>=1.3.0
Requires-Dist: proselint>=0.13.0
Requires-Dist: rich>=12.5.1
Provides-Extra: dev
Requires-Dist: pytest>=7.0; extra == "dev"
Requires-Dist: pytest-cov>=4.0; extra == "dev"
Requires-Dist: ruff>=0.1.0; extra == "dev"
Requires-Dist: mypy>=1.0; extra == "dev"
Requires-Dist: pre-commit>=3.0; extra == "dev"
Requires-Dist: tox>=4.0; extra == "dev"
Provides-Extra: test
Requires-Dist: pytest>=7.0; extra == "test"
Requires-Dist: pytest-cov>=4.0; extra == "test"
Dynamic: license-file
